{
 "version": 1,
 "key_columns": [
  "relation_id"
 ],
 "by_key": {
  "44547679@6_0-44547679@6_17": {
   "is_correct": true
  },
  "312906@7_0-312906@7_9": {
   "is_correct": true
  },
  "37112829@22_0-37112829@22_9": {
   "is_correct": true
  },
  "26193506@5_0-26193506@5_5": {
   "is_correct": true
  },
  "7680815@4_0-7680815@4_9": {
   "is_correct": true
  },
  "22436080@2_0-22436080@2_5": {
   "is_correct": true
  },
  "216970@8_0-216970@8_18": {
   "is_correct": true
  },
  "796578@9_0-796578@9_8": {
   "is_correct": true
  },
  "1483701@11_0-1483701@11_7": {
   "is_correct": true
  },
  "206644@3_0-206644@3_14": {
   "is_correct": true
  },
  "14974304@19_0-14974304@19_4": {
   "is_correct": true
  },
  "2665349@3_0-2665349@3_15": {
   "is_correct": true
  },
  "22232231@7_0-22232231@7_6": {
   "is_correct": true
  },
  "17464172@3_0-17464172@3_7": {
   "is_correct": true
  },
  "295561@3_0-295561@3_15": {
   "is_correct": true
  },
  "336988@6_0-336988@6_19": {
   "is_correct": true
  },
  "2197689@3_0-2197689@3_18": {
   "is_correct": true
  },
  "12303441@6_0-12303441@6_14": {
   "is_correct": true
  },
  "2105152@5_0-2105152@5_15": {
   "is_correct": true
  },
  "10603738@3_0-10603738@3_6": {
   "is_correct": true
  },
  "10291466@8_0-10291466@8_7": {
   "is_correct": true
  },
  "500700@11_0-500700@11_13": {
   "is_correct": true
  },
  "172055@5_0-172055@5_8": {
   "is_correct": true
  },
  "1978013@6_0-1978013@6_19": {
   "is_correct": true
  },
  "11554761@5_0-11554761@5_25": {
   "is_correct": true
  },
  "26289187@4_0-26289187@4_5": {
   "is_correct": true
  },
  "18538277@5_0-18538277@5_9": {
   "is_correct": true
  },
  "1397886@6_0-1397886@6_13": {
   "is_correct": true
  },
  "1822230@3_0-1822230@3_20": {
   "is_correct": true
  },
  "21457841@5_0-21457841@5_13": {
   "is_correct": true
  },
  "305256@23_0-305256@23_19": {
   "is_correct": true
  },
  "37905898@6_0-37905898@6_8": {
   "is_correct": true
  },
  "46386@19_0-46386@19_14": {
   "is_correct": true
  },
  "10312823@5_0-10312823@5_5": {
   "is_correct": true
  },
  "6221025@3_0-6221025@3_10": {
   "is_correct": true
  },
  "15120409@5_0-15120409@5_24": {
   "is_correct": false
  },
  "403293@227_0-403293@227_11": {
   "is_correct": true
  },
  "6899772@3_0-6899772@3_5": {
   "is_correct": true
  },
  "26623175@4_0-26623175@4_13": {
   "is_correct": true
  },
  "68378@5_0-68378@5_7": {
   "is_correct": true
  },
  "1134871@2_0-1134871@2_5": {
   "is_correct": true
  },
  "3380777@3_0-3380777@3_8": {
   "is_correct": true
  },
  "1784933@5_0-1784933@5_21": {
   "is_correct": true
  },
  "36567170@5_4-36567170@5_9": {
   "is_correct": true
  },
  "5552759@98_0-5552759@98_9": {
   "is_correct": true
  },
  "31165451@4_0-31165451@4_12": {
   "is_correct": true
  },
  "6064346@9_0-6064346@9_18": {
   "is_correct": true
  },
  "1261718@4_0-1261718@4_4": {
   "is_correct": true
  },
  "14041198@3_0-14041198@3_9": {
   "is_correct": true
  },
  "747491@4_0-747491@4_18": {
   "is_correct": true
  },
  "23715746@3_12-23715746@3_17": {
   "is_correct": true
  },
  "4676585@2_0-4676585@2_7": {
   "is_correct": true
  },
  "42190822@2_0-42190822@2_5": {
   "is_correct": true
  },
  "6743683@6_0-6743683@6_5": {
   "is_correct": true
  },
  "453510@4_0-453510@4_10": {
   "is_correct": true
  },
  "5674370@4_0-5674370@4_7": {
   "is_correct": true
  },
  "35107556@3_0-35107556@3_5": {
   "is_correct": true
  },
  "8309203@2_0-8309203@2_13": {
   "is_correct": true
  },
  "34432279@4_0-34432279@4_5": {
   "is_correct": true
  },
  "158291@3_0-158291@3_18": {
   "is_correct": true
  },
  "69089@8_0-69089@8_5": {
   "is_correct": true
  },
  "33363072@3_0-33363072@3_6": {
   "is_correct": true
  },
  "7710901@4_0-7710901@4_6": {
   "is_correct": true
  },
  "530861@6_0-530861@6_5": {
   "is_correct": true
  },
  "33985168@37_0-33985168@37_6": {
   "is_correct": true
  },
  "40650034@3_0-40650034@3_9": {
   "is_correct": true
  },
  "3841754@16_0-3841754@16_4": {
   "is_correct": true
  },
  "46226@13_0-46226@13_22": {
   "is_correct": true
  },
  "23830110@4_0-23830110@4_12": {
   "is_correct": true
  },
  "481537@18_0-481537@18_9": {
   "is_correct": true
  },
  "472272@5_0-472272@5_16": {
   "is_correct": true
  },
  "26297513@6_0-26297513@6_12": {
   "is_correct": true
  },
  "567174@10_0-567174@10_11": {
   "is_correct": true
  },
  "20900543@3_0-20900543@3_9": {
   "is_correct": true
  },
  "33626469@4_0-33626469@4_16": {
   "is_correct": true
  },
  "7071808@3_0-7071808@3_7": {
   "is_correct": true
  },
  "2511247@3_0-2511247@3_17": {
   "is_correct": true
  },
  "2643171@9_0-2643171@9_7": {
   "is_correct": true
  },
  "36671306@3_0-36671306@3_8": {
   "is_correct": true
  },
  "779475@3_0-779475@3_18": {
   "is_correct": true
  },
  "27002743@2_0-27002743@2_10": {
   "is_correct": true
  },
  "35904970@1_0-35904970@1_26": {
   "is_correct": true
  },
  "43490475@3_0-43490475@3_6": {
   "is_correct": true
  },
  "1622342@2_0-1622342@2_9": {
   "is_correct": true
  },
  "36916872@18_0-36916872@18_5": {
   "is_correct": true
  },
  "91130@4_0-91130@4_17": {
   "is_correct": true
  },
  "39213072@3_0-39213072@3_5": {
   "is_correct": true
  },
  "14216641@5_0-14216641@5_22": {
   "is_correct": true
  },
  "28354259@6_0-28354259@6_8": {
   "is_correct": true
  },
  "32899084@3_0-32899084@3_9": {
   "is_correct": true
  },
  "33530293@2_0-33530293@2_5": {
   "is_correct": true
  },
  "38468822@6_0-38468822@6_6": {
   "is_correct": true
  },
  "9892967@3_0-9892967@3_11": {
   "is_correct": true
  },
  "1962338@7_0-1962338@7_12": {
   "is_correct": true
  },
  "4650153@72_0-4650153@72_9": {
   "is_correct": true
  },
  "42978479@35_0-42978479@35_17": {
   "is_correct": true
  },
  "5182508@5_0-5182508@5_11": {
   "is_correct": true
  },
  "6380473@6_0-6380473@6_6": {
   "is_correct": true
  },
  "24984248@4_0-24984248@4_7": {
   "is_correct": true
  },
  "5396845@3_0-5396845@3_9": {
   "is_correct": true
  }
 }
}